gestion_banco_taipe/__init__.py
gestion_banco_taipe/modulo.py
gestion_banco_taipe-1.0.0.dist-info/METADATA
gestion_banco_taipe-1.0.0.dist-info/WHEEL
gestion_banco_taipe-1.0.0.dist-info/top_level.txt
gestion_banco_taipe-1.0.0.dist-info/RECORD
