Metadata-Version: 2.4
Name: gestion_banco_taipe
Version: 1.0.0
Summary: Paquete para gestión bancaria con POO en Python
Author: Ángel Taipe
Author-email: angeltaipe364@gmail.com
License: MIT
Requires-Python: >=3.7
Dynamic: author
Dynamic: author-email
Dynamic: description
Dynamic: description-content-type
Dynamic: license
Dynamic: requires-python
Dynamic: summary
